bleu_mp/__init__.py
bleu_mp/bleu_mp.py
bleu_mp-0.0.1.dist-info/LICENSE
bleu_mp-0.0.1.dist-info/METADATA
bleu_mp-0.0.1.dist-info/WHEEL
bleu_mp-0.0.1.dist-info/top_level.txt
bleu_mp-0.0.1.dist-info/RECORD
