Metadata-Version: 2.1
Name: bleu-mp
Version: 0.0.1
Summary: Multi-process bleu evaluation.
Home-page: https://github.com/One-sixth/bleu-mp
Author: onesixth
Author-email: noexist@noexist.noexist
Classifier: Programming Language :: Python :: 3
Classifier: License :: OSI Approved :: MIT License
Classifier: Operating System :: POSIX :: Linux
Classifier: Operating System :: Microsoft :: Windows
License-File: LICENSE
